Metadata-Version: 1.2
Name: galoup
Version: 0.0.4a0
Summary: Galoup is a Python framework for rolling your own project management tool.
Home-page: https://github.com/liampulles/galoup
Author: Liam Pulles
Author-email: me@liampulles.com
License: MIT
Platform: UNKNOWN
Classifier: Development Status :: 3 - Alpha
Classifier: Intended Audience :: Developers
Classifier: Programming Language :: Python :: 3
Classifier: Programming Language :: Python :: 3.4
Classifier: Programming Language :: Python :: 3.5
Classifier: Programming Language :: Python :: 3.6
Classifier: Programming Language :: Python :: 3.7
Classifier: License :: OSI Approved :: MIT License
Classifier: Operating System :: OS Independent
Requires-Python: >=3.4
